lex_yacc_calc/__init__.py
lex_yacc_calc/calc.py
lex_yacc_calc/parsetab.py
lex_yacc_calc-0.0.1.dist-info/LICENSE
lex_yacc_calc-0.0.1.dist-info/METADATA
lex_yacc_calc-0.0.1.dist-info/WHEEL
lex_yacc_calc-0.0.1.dist-info/top_level.txt
lex_yacc_calc-0.0.1.dist-info/RECORD
