Metadata-Version: 2.1
Name: lex-yacc-calc
Version: 0.0.1
Summary: For tokenizing and then creating AST using PLY
Home-page: UNKNOWN
Author: Souhardya Chakrabarti & Soumadip Pal
Author-email: jackhammer2662@gmail.com
License: UNKNOWN
Platform: UNKNOWN
Classifier: Programming Language :: Python :: 3
Classifier: License :: OSI Approved :: MIT License
Classifier: Operating System :: OS Independent
Requires-Python: >=3.7
License-File: LICENSE
